openpivtlib/__init__.py
openpivtlib/plugin.py
openpivtlib/util.py
unittests/__init__.py
unittests/test_plugin.py
unittests/test_util.py
openpivtlib-1.2.3.dist-info/METADATA
openpivtlib-1.2.3.dist-info/WHEEL
openpivtlib-1.2.3.dist-info/top_level.txt
openpivtlib-1.2.3.dist-info/RECORD
