Metadata-Version: 2.1
Name: openpivtlib
Version: 1.2.3
Summary: A library containing common elements to openpivt and PIVT apps built on top of openpivt
Home-page: UNKNOWN
Author: Eric Frechette
Author-email: eric@softwarefactorylabs.com
License: UNKNOWN
Platform: UNKNOWN
Classifier: Programming Language :: Python
Classifier: Intended Audience :: Developers
Requires-Python: >=3.8,<3.9
Provides-Extra: dev
Requires-Dist: pytest (==6.2.1) ; extra == 'dev'
Requires-Dist: pytest-cov (==2.10.1) ; extra == 'dev'
Requires-Dist: codecov (==2.1.11) ; extra == 'dev'
Requires-Dist: pylint (==2.6.0) ; extra == 'dev'
